pdxwave/Backsys.py
pdxwave/SPNKit.py
pdxwave/__init__.py
pdxwave-0.0.5.dist-info/METADATA
pdxwave-0.0.5.dist-info/WHEEL
pdxwave-0.0.5.dist-info/entry_points.txt
pdxwave-0.0.5.dist-info/top_level.txt
pdxwave-0.0.5.dist-info/RECORD
