Metadata-Version: 2.1
Name: pdxwave
Version: 0.0.5
Requires-Dist: requests
